jupyterlmod/__init__.py
jupyterlmod/config.py
jupyterlmod/handler.py
jupyterlmod/etc/jupyterlmod_jupyterserverextension.json
jupyterlmod/etc/jupyterlmod_nbextension.json
jupyterlmod/etc/jupyterlmod_serverextension.json
jupyterlmod/labextension/package.json
jupyterlmod/labextension/static/307.33b185b8652e137e1073.js
jupyterlmod/labextension/static/665.8c4efd4acb8d64ec3621.js
jupyterlmod/labextension/static/688.547f6ac630347c348b7d.js
jupyterlmod/labextension/static/980.28a70f5cb5d65a767b64.js
jupyterlmod/labextension/static/remoteEntry.fafca51b83de1844c8a9.js
jupyterlmod/labextension/static/style.js
jupyterlmod/labextension/static/third-party-licenses.json
jupyterlmod/static/main.js
jupyterlmod/static/module.js
jupyterlmod/static/logos/lmod.png
jupyterlmod/static/logos/tmod.png
module/__init__.py
jupyterlmod-5.3.0.data/data/etc/jupyter/jupyter_notebook_config.d/jupyterlmod_serverextension.json
jupyterlmod-5.3.0.data/data/etc/jupyter/jupyter_server_config.d/jupyterlmod_jupyterserverextension.json
jupyterlmod-5.3.0.data/data/share/jupyter/nbextensions/jupyterlmod/main.js
jupyterlmod-5.3.0.data/data/share/jupyter/nbextensions/jupyterlmod/module.js
jupyterlmod-5.3.0.data/data/share/jupyter/nbextensions/jupyterlmod/logos/lmod.png
jupyterlmod-5.3.0.data/data/share/jupyter/nbextensions/jupyterlmod/logos/tmod.png
jupyterlmod-5.3.0.data/data/etc/jupyter/nbconfig/tree.d/jupyterlmod_nbextension.json
jupyterlmod-5.3.0.data/data/share/jupyter/labextensions/@cmd-ntrf/jupyterlab-lmod/package.json
jupyterlmod-5.3.0.data/data/share/jupyter/labextensions/@cmd-ntrf/jupyterlab-lmod/static/307.33b185b8652e137e1073.js
jupyterlmod-5.3.0.data/data/share/jupyter/labextensions/@cmd-ntrf/jupyterlab-lmod/static/665.8c4efd4acb8d64ec3621.js
jupyterlmod-5.3.0.data/data/share/jupyter/labextensions/@cmd-ntrf/jupyterlab-lmod/static/688.547f6ac630347c348b7d.js
jupyterlmod-5.3.0.data/data/share/jupyter/labextensions/@cmd-ntrf/jupyterlab-lmod/static/980.28a70f5cb5d65a767b64.js
jupyterlmod-5.3.0.dist-info/METADATA
jupyterlmod-5.3.0.dist-info/WHEEL
jupyterlmod-5.3.0.dist-info/licenses/LICENSE
jupyterlmod-5.3.0.dist-info/RECORD
