Metadata-Version: 2.4
Name: jupyterlmod
Version: 5.3.0
Dynamic: Keywords
Summary: Lmod/Tmod JupyterLab extension
Project-URL: Homepage, https://github.com/cmd-ntrf/jupyter-lmod
Project-URL: Bug Tracker, https://github.com/cmd-ntrf/jupyter-lmod/issues
Project-URL: Repository, https://github.com/cmd-ntrf/jupyter-lmod.git
Author-email: Felix-Antoine Fortin <felix@calculquebec.ca>
License: MIT License
License-File: LICENSE
Classifier: Framework :: Jupyter
Classifier: License :: OSI Approved :: BSD License
Classifier: Programming Language :: Python
Classifier: Programming Language :: Python :: 3
Classifier: Programming Language :: Python :: 3.6
Classifier: Programming Language :: Python :: 3.7
Classifier: Programming Language :: Python :: 3.8
Classifier: Programming Language :: Python :: 3.9
Classifier: Programming Language :: Python :: 3.10
Requires-Python: >=3.6
Requires-Dist: jupyter-core
Requires-Dist: jupyter-server
